raspauto/__init__.py
raspauto-0.3.1.dist-info/LICENSE
raspauto-0.3.1.dist-info/METADATA
raspauto-0.3.1.dist-info/WHEEL
raspauto-0.3.1.dist-info/top_level.txt
raspauto-0.3.1.dist-info/RECORD
