Metadata-Version: 2.1
Name: raspauto
Version: 0.3.1
Summary: Raspberry Automation Library and Voice Recognition
Home-page: https://github.com/aattk/raspauto
Download-URL: https://pypi.org/project/raspauto/
Author: Alpaslan Tetik
Author-email: 232arslan104@gmail.com
License: GNU
Keywords: raspberry,automotion,control
Requires-Python: >=3.6
License-File: LICENSE
Requires-Dist: python-telegram-bot
